gravitynet/__init__.py
gravitynet/gravitypoints/__init__.py
gravitynet/gravitypoints/gravity_points_config.py
gravitynet/gravitypoints/draw/__init__.py
gravitynet/gravitypoints/draw/draw_gravity_points.py
gravitynet/gravitypoints/initial_config/__init__.py
gravitynet/gravitypoints/initial_config/initial_dice_config.py
gravitynet/gravitypoints/initial_config/initial_grid_config.py
gravitynet/gravitypoints/utility/__init__.py
gravitynet/gravitypoints/utility/check_image_shape.py
gravitynet/gravitypoints/utility/get_feature_grid.py
gravitynet/gravitypoints/utility/get_feature_map.py
gravitynet/gravitypoints/utility/get_num_gravity_points.py
gravitynet/gravitypoints/utility/shift.py
gravitynet/loss/GravityLoss.py
gravitynet/loss/__init__.py
gravitynet/model/GravityNet.py
gravitynet/model/__init__.py
gravitynet/model/backbone/MyDenseNet_models.py
gravitynet/model/backbone/MyEfficientNetV2_models.py
gravitynet/model/backbone/MyEfficientNet_models.py
gravitynet/model/backbone/MyResNeXt_models.py
gravitynet/model/backbone/MyResNet_models.py
gravitynet/model/backbone/MySwin_models.py
gravitynet/model/backbone/__init__.py
gravitynet/model/backbone/DenseNet/MyDenseNet121.py
gravitynet/model/backbone/DenseNet/MyDenseNet161.py
gravitynet/model/backbone/DenseNet/MyDenseNet169.py
gravitynet/model/backbone/DenseNet/MyDenseNet201.py
gravitynet/model/backbone/DenseNet/__init__.py
gravitynet/model/backbone/EfficientNet/MyEfficientNetB0.py
gravitynet/model/backbone/EfficientNet/MyEfficientNetB1.py
gravitynet/model/backbone/EfficientNet/MyEfficientNetB2.py
gravitynet/model/backbone/EfficientNet/MyEfficientNetB3.py
gravitynet/model/backbone/EfficientNet/MyEfficientNetB4.py
gravitynet/model/backbone/EfficientNet/MyEfficientNetB5.py
gravitynet/model/backbone/EfficientNet/MyEfficientNetB6.py
gravitynet/model/backbone/EfficientNet/MyEfficientNetB7.py
gravitynet/model/backbone/EfficientNet/__init__.py
gravitynet/model/backbone/EfficientNetV2/MyEfficientNetV2L.py
gravitynet-0.0.11.dist-info/LICENSE
gravitynet-0.0.11.dist-info/METADATA
gravitynet-0.0.11.dist-info/WHEEL
gravitynet-0.0.11.dist-info/top_level.txt
gravitynet-0.0.11.dist-info/RECORD
