Metadata-Version: 2.1
Name: gravitynet
Version: 0.0.11
Summary: gravitynet package
Home-page: https://github.com/cirorusso2910/GravityNet
Author: Ciro Russo, Giulio Russo
Author-email: ciro.russo2910@gmail.com
License: MIT License
Classifier: Programming Language :: Python :: 3
Classifier: License :: OSI Approved :: MIT License
Classifier: Operating System :: OS Independent
Requires-Python: >=3.8.0
License-File: LICENSE
Requires-Dist: setuptools ==60.2.0
Requires-Dist: numpy ==1.23.5
Requires-Dist: torch ==1.12.0
Requires-Dist: torchvision ==0.13.0
Requires-Dist: opencv-python ==4.11.0.86
